eox_theming/__init__.py
eox_theming/apps.py
eox_theming/test_module.py
eox_theming/test_utils.py
eox_theming/urls.py
eox_theming/configuration/__init__.py
eox_theming/edxapp_wrapper/__init__.py
eox_theming/edxapp_wrapper/config_sources.py
eox_theming/edxapp_wrapper/configuration_helpers.py
eox_theming/edxapp_wrapper/finders.py
eox_theming/edxapp_wrapper/loaders.py
eox_theming/edxapp_wrapper/mako.py
eox_theming/edxapp_wrapper/models.py
eox_theming/edxapp_wrapper/storage.py
eox_theming/edxapp_wrapper/theming_helpers.py
eox_theming/edxapp_wrapper/backends/__init__.py
eox_theming/edxapp_wrapper/backends/j_configuration_helpers.py
eox_theming/edxapp_wrapper/backends/j_configuration_helpers_tests.py
eox_theming/edxapp_wrapper/backends/j_finders.py
eox_theming/edxapp_wrapper/backends/j_loaders.py
eox_theming/edxapp_wrapper/backends/j_loaders_tests.py
eox_theming/edxapp_wrapper/backends/j_mako_tests.py
eox_theming/edxapp_wrapper/backends/j_models.py
eox_theming/edxapp_wrapper/backends/j_theming_helpers.py
eox_theming/edxapp_wrapper/backends/j_theming_helpers_tests.py
eox_theming/edxapp_wrapper/backends/l_mako.py
eox_theming/edxapp_wrapper/backends/l_storage.py
eox_theming/edxapp_wrapper/tests/__init__.py
eox_theming/edxapp_wrapper/tests/integration/__init__.py
eox_theming/edxapp_wrapper/tests/integration/test_backends.py
eox_theming/management/__init__.py
eox_theming/management/urls.py
eox_theming/management/views.py
eox_theming/management/tests/__init__.py
eox_theming/management/tests/integration/__init__.py
eox_theming/management/tests/integration/test_views.py
eox_theming/settings/__init__.py
eox_theming/settings/common.py
eox_theming/settings/devstack.py
eox_theming/settings/production.py
eox_theming/settings/test.py
eox_theming/templatetags/__init__.py
eox_theming/templatetags/eox_theming.py
eox_theming/tests/__init__.py
eox_theming/tests/test_configuration.py
eox_theming/tests/test_templatetags.py
eox_theming/tests/management/__init__.py
eox_theming-9.3.1.dist-info/licenses/AUTHORS.txt
eox_theming-9.3.1.dist-info/licenses/LICENSE.txt
eox_theming-9.3.1.dist-info/METADATA
eox_theming-9.3.1.dist-info/WHEEL
eox_theming-9.3.1.dist-info/entry_points.txt
eox_theming-9.3.1.dist-info/top_level.txt
eox_theming-9.3.1.dist-info/RECORD
